asktable/__init__.py
asktable/_base_client.py
asktable/_client.py
asktable/_compat.py
asktable/_constants.py
asktable/_exceptions.py
asktable/_files.py
asktable/_models.py
asktable/_qs.py
asktable/_resource.py
asktable/_response.py
asktable/_streaming.py
asktable/_types.py
asktable/_version.py
asktable/pagination.py
asktable/py.typed
asktable/_utils/__init__.py
asktable/_utils/_logs.py
asktable/_utils/_proxy.py
asktable/_utils/_reflection.py
asktable/_utils/_resources_proxy.py
asktable/_utils/_streams.py
asktable/_utils/_sync.py
asktable/_utils/_transform.py
asktable/_utils/_typing.py
asktable/_utils/_utils.py
asktable/lib/.keep
asktable/resources/__init__.py
asktable/resources/answers.py
asktable/resources/auth.py
asktable/resources/bots.py
asktable/resources/business_glossary.py
asktable/resources/caches.py
asktable/resources/dataframes.py
asktable/resources/files.py
asktable/resources/integration.py
asktable/resources/policies.py
asktable/resources/polish.py
asktable/resources/preferences.py
asktable/resources/project.py
asktable/resources/roles.py
asktable/resources/scores.py
asktable/resources/securetunnels.py
asktable/resources/sqls.py
asktable/resources/trainings.py
asktable/resources/chats/__init__.py
asktable/resources/chats/chats.py
asktable/resources/chats/messages.py
asktable/resources/datasources/__init__.py
asktable/resources/datasources/datasources.py
asktable/resources/datasources/indexes.py
asktable/resources/datasources/meta.py
asktable/resources/datasources/upload_params.py
asktable/resources/extapis/__init__.py
asktable/resources/extapis/extapis.py
asktable/resources/extapis/routes.py
asktable/resources/sys/__init__.py
asktable/resources/sys/sys.py
asktable/resources/sys/projects/__init__.py
asktable/resources/sys/projects/api_keys.py
asktable/resources/sys/projects/projects.py
asktable/types/__init__.py
asktable/types/ai_message.py
asktable/types/answer_create_params.py
asktable/types/answer_list_params.py
asktable/types/answer_response.py
asktable-5.4.0.dist-info/METADATA
asktable-5.4.0.dist-info/WHEEL
asktable-5.4.0.dist-info/licenses/LICENSE
asktable-5.4.0.dist-info/RECORD
